filesharecli/__init__.py
filesharecli/filesharecli.py
filesharecli-1.0.0.dist-info/METADATA
filesharecli-1.0.0.dist-info/WHEEL
filesharecli-1.0.0.dist-info/entry_points.txt
filesharecli-1.0.0.dist-info/top_level.txt
filesharecli-1.0.0.dist-info/RECORD
