Metadata-Version: 2.4
Name: filesharecli
Version: 1.0.0
Summary: FileShareCLI is a simple yet powerful Python-based CLI tool that lets developers share files and command snippets effortlessly from the terminal.
Home-page: https://github.com/lmas3009/filesharecli-pip
Author: Aravind Kumar Vemula
Author-email: 30lmas09@gmail.com
Classifier: Intended Audience :: Developers
Classifier: Programming Language :: Python :: 3
Classifier: Operating System :: Unix
Classifier: Operating System :: MacOS :: MacOS X
Classifier: Operating System :: Microsoft :: Windows
Requires-Python: >=3.8
Requires-Dist: requests
Requires-Dist: colorama
Dynamic: author
Dynamic: author-email
Dynamic: classifier
Dynamic: description
Dynamic: description-content-type
Dynamic: home-page
Dynamic: requires-dist
Dynamic: requires-python
Dynamic: summary
